n_sphere/__init__.py
n_sphere/n_sphere.py
n_sphere-1.2.0.dist-info/LICENSE
n_sphere-1.2.0.dist-info/METADATA
n_sphere-1.2.0.dist-info/WHEEL
n_sphere-1.2.0.dist-info/top_level.txt
n_sphere-1.2.0.dist-info/RECORD
